iree/_runtime.cpython-311-darwin.so
iree/runtime/__init__.py
iree/runtime/_binding.py
iree/runtime/array_interop.py
iree/runtime/benchmark.py
iree/runtime/flags.py
iree/runtime/function.py
iree/runtime/iree-benchmark-module
iree/runtime/iree-benchmark-trace
iree/runtime/iree-run-module
iree/runtime/iree-run-trace
iree/runtime/system_api.py
iree/runtime/system_setup.py
iree/runtime/tracing.py
iree/runtime/version.py
iree/runtime/scripts/iree_benchmark_module/__main__.py
iree/runtime/scripts/iree_benchmark_trace/__main__.py
iree/runtime/scripts/iree_run_module/__main__.py
iree/runtime/scripts/iree_run_trace/__main__.py
iree/runtime/scripts/iree_tracy_capture/__main__.py
iree_runtime_instrumented.egg-info/PKG-INFO
iree_runtime_instrumented.egg-info/SOURCES.txt
iree_runtime_instrumented.egg-info/dependency_links.txt
iree_runtime_instrumented.egg-info/entry_points.txt
iree_runtime_instrumented.egg-info/not-zip-safe
iree_runtime_instrumented.egg-info/requires.txt
iree_runtime_instrumented.egg-info/top_level.txt
iree_runtime_instrumented-20230524.529.dist-info/METADATA
iree_runtime_instrumented-20230524.529.dist-info/WHEEL
iree_runtime_instrumented-20230524.529.dist-info/entry_points.txt
iree_runtime_instrumented-20230524.529.dist-info/top_level.txt
iree_runtime_instrumented-20230524.529.dist-info/RECORD
